pyventim/__init__.py
pyventim/adapters.py
pyventim/eventim.py
pyventim/exceptions.py
pyventim/models.py
pyventim/utils.py
pyventim-0.2.0.dist-info/LICENCE.md
pyventim-0.2.0.dist-info/METADATA
pyventim-0.2.0.dist-info/WHEEL
pyventim-0.2.0.dist-info/top_level.txt
pyventim-0.2.0.dist-info/RECORD
