Metadata-Version: 2.1
Name: pyventim
Version: 0.2.0
Summary: Python wrapper to fetch a reverse engineered Eventim API.
Author-email: Kilian Braun <hello@kilianbraun.de>
Maintainer-email: Kilian Braun <hello@kilianbraun.de>
Project-URL: Homepage, https://github.com/kggx/pyventim
Project-URL: Issues, https://github.com/kggx/pyventim/issues
Project-URL: Documentation, https://kggx.github.io/pyventim/pyventim.html
Classifier: Programming Language :: Python :: 3.10
Classifier: Programming Language :: Python :: 3.11
Classifier: Programming Language :: Python :: 3.12
Classifier: License :: OSI Approved :: MIT License
Classifier: Operating System :: OS Independent
Requires-Python: >=3.10
License-File: LICENCE.md
Requires-Dist: requests >=2.31.0
Requires-Dist: lxml >=5.2.0
Requires-Dist: pydantic >=2.7.0
Provides-Extra: dev
Requires-Dist: requests >=2.31.0 ; extra == 'dev'
Requires-Dist: lxml >=5.2.2 ; extra == 'dev'
Requires-Dist: pydantic >=2.7.0 ; extra == 'dev'
Requires-Dist: flake8 >=7.0.0 ; extra == 'dev'
Requires-Dist: pytest-cov >=5.0.0 ; extra == 'dev'
Requires-Dist: pytest >=8.2.0 ; extra == 'dev'
Requires-Dist: black >=24.4.0 ; extra == 'dev'
Requires-Dist: pdoc >=14.4.0 ; extra == 'dev'
Requires-Dist: twine >=5.1.0 ; extra == 'dev'
Requires-Dist: build >=1.2.1 ; extra == 'dev'
Requires-Dist: Pillow ; extra == 'dev'
